LICENSE
README.rst
pyproject.toml
simplecalc/__init__.py
simplecalc/calculator.py
simplecalc/cli.py
simplecalc/tests/__init__.py
simplecalc/tests/test_calculator.py
simplecalc/tests/test_cli.py
simplecalc-0.1.0.dist-info/entry_points.txt
simplecalc-0.1.0.dist-info/LICENSE
simplecalc-0.1.0.dist-info/WHEEL
simplecalc-0.1.0.dist-info/METADATA
simplecalc-0.1.0.dist-info/RECORD
