Metadata-Version: 2.1
Name: simplecalc
Version: 0.1.0
Summary: A simple calculator to demonstrate python tooling
Home-page: https://simplecalc.readthedocs.io
License: MIT
Author: Adithya Balaji
Author-email: adithyabsk@gmail.com
Requires-Python: >=3.6,<4.0
Classifier: License :: OSI Approved :: MIT License
Classifier: Programming Language :: Python :: 3
Classifier: Programming Language :: Python :: 3.6
Classifier: Programming Language :: Python :: 3.7
Provides-Extra: doc
Requires-Dist: click (>=7.0,<8.0)
Requires-Dist: sphinx (>=2.1,<3.0); extra == "doc"
Requires-Dist: sphinx_rtd_theme (>=0.4.3,<0.5.0); extra == "doc"
Requires-Dist: toml (>=0.10.0,<0.11.0)
Project-URL: Documentation, https://simplecalc.readthedocs.io
Project-URL: Repository, https://github.com/adithyabsk/simplecalc
